orm_collector/.gitignore
orm_collector/__init__.py
orm_collector/api/app.py
orm_collector/api/worker.py
orm_collector/crear_tabla.py~
orm_collector/create_db.py
orm_collector/csv2json.py
orm_collector/db_session.py
orm_collector/generate_schema.py
orm_collector/load_data.py
orm_collector/load_short_data.py
orm_collector/manager.py
orm_collector/manager.py~
orm_collector/models.py
orm_collector/scripts/crear_tabla.py
orm_collector/scripts/create_db.py
orm_collector/scripts/csv2json.py
orm_collector/scripts/dbdata_example.json
orm_collector/scripts/dbdata_example.json~
orm_collector/scripts/envs.sh
orm_collector/scripts/filenames.json
orm_collector/scripts/load_data.py
orm_collector/scripts/show_data.py
orm_collector/scripts/test.json
orm_collector/scripts/update_station.py
orm_collector/sql/CREAR_DB.sql
orm_collector/sql/DROP.sql
orm_collector/sql/activve_column_bool.sql
orm_collector/sql/create_collector.sh
orm_collector/sql/dbdata_query.sql
orm_collector/sql/dbserver_query.sql
orm_collector/sql/dbtest.sql
orm_collector/sql/dbtest.sql~
orm_collector/sql/drop_collector.sh
orm_collector/sql/foreign_key.sql
orm_collector/sql/station_query.sql
orm_collector/sql/test_station.sql
orm_collector/sql/test_station.sql~
orm_collector/update_station.py
orm_collector/validates.py
orm_collector-2.0.21.dist-info/METADATA
orm_collector-2.0.21.dist-info/WHEEL
orm_collector-2.0.21.dist-info/entry_points.txt
orm_collector-2.0.21.dist-info/RECORD
